{
    "version": "2026.03.03",
    "description": "A youtube-dl fork with additional features and fixes.",
    "homepage": "https://github.com/yt-dlp/yt-dlp",
    "license": "Unlicense",
    "suggest": {
        "ffmpeg": "ffmpeg"
    },
    "architecture": {
        "64bit": {
            "url": "https://github.com/yt-dlp/yt-dlp/releases/download/2026.03.03/yt-dlp.exe",
            "hash": "sha512:09ca2436b2aa0c6426d191dfd277bfe3607eb8c85f9911aae518a9ecc76ddb9a1e3ebe58bc82cc768dd3506cd3961f95178639e64ab67d9714f28c1a7113af1e"
        }
    },
    "bin": "yt-dlp.exe",
    "pre_install": "if (-not (Test-Path \"$persist_dir\\yt-dlp.conf\")) { New-Item \"$dir\\yt-dlp.conf\" -ItemType file | Out-Null }",
    "persist": [
        "yt-dlp.conf",
        "ytdlp_plugins"
    ],
    "checkver": "github",
    "autoupdate": {
        "architecture": {
            "64bit": {
                "url": "https://github.com/yt-dlp/yt-dlp/releases/download/$version/yt-dlp.exe"
            }
        },
        "hash": {
            "url": "$baseurl/SHA2-512SUMS"
        }
    }
}
