{
    "version": "2025.02.19",
    "description": "A youtube-dl fork with additional features and fixes.",
    "homepage": "https://github.com/yt-dlp/yt-dlp",
    "license": "Unlicense",
    "suggest": {
        "ffmpeg": "ffmpeg"
    },
    "architecture": {
        "64bit": {
            "url": "https://github.com/yt-dlp/yt-dlp/releases/download/2025.02.19/yt-dlp.exe",
            "hash": "sha512:77e497d07c9eebe1ddb0728d324a3536e63f4d1b558f3ff57decab928f60780a7fd8f3cbab9b6da2cb5387f27f7e62bbb47e75941a5b7fe1af2ec0f0a1bd4fdb"
        }
    },
    "bin": "yt-dlp.exe",
    "pre_install": "if (-not (Test-Path \"$persist_dir\\yt-dlp.conf\")) { New-Item \"$dir\\yt-dlp.conf\" -ItemType file | Out-Null }",
    "persist": [
        "yt-dlp.conf",
        "ytdlp_plugins"
    ],
    "checkver": "github",
    "autoupdate": {
        "architecture": {
            "64bit": {
                "url": "https://github.com/yt-dlp/yt-dlp/releases/download/$version/yt-dlp.exe"
            }
        },
        "hash": {
            "url": "$baseurl/SHA2-512SUMS"
        }
    }
}
